aioircd/__init__.py
aioircd/__main__.py
aioircd/channel.py
aioircd/config.py
aioircd/exceptions.py
aioircd/sdnotify.py
aioircd/server.py
aioircd/states.py
aioircd/user.py
aioircd-2.0.6.dist-info/LICENSE
aioircd-2.0.6.dist-info/METADATA
aioircd-2.0.6.dist-info/WHEEL
aioircd-2.0.6.dist-info/top_level.txt
aioircd-2.0.6.dist-info/RECORD
