Metadata-Version: 2.1
Name: aioircd
Version: 2.0.6
Summary: A minimalist asynchronous IRC server
Home-page: https://github.com/readthedocs-fr/aioircd
Author: Julien Castiaux
Author-email: julien.castiaux@gmail.com
License: MIT
Download-URL: https://pypi.python.org/project/aioircd/
Platform: UNKNOWN
Classifier: Environment :: No Input/Output (Daemon)
Classifier: Framework :: AsyncIO
Classifier: License :: OSI Approved :: MIT License
Classifier: Operating System :: OS Independent
Classifier: Programming Language :: Python :: 3 :: Only
Classifier: Topic :: Communications :: Chat :: Internet Relay Chat
Requires-Python: >=3.9
License-File: LICENSE
Requires-Dist: trio
